tetration/__init__.py
tetration/tetration.py
tetration-0.0.2.dist-info/METADATA
tetration-0.0.2.dist-info/WHEEL
tetration-0.0.2.dist-info/licenses/LICENSE
tetration-0.0.2.dist-info/RECORD
